mydaoyipackage/DaoYi.py
mydaoyipackage/__init__.py
mydaoyipackage-0.0.3.dist-info/METADATA
mydaoyipackage-0.0.3.dist-info/WHEEL
mydaoyipackage-0.0.3.dist-info/top_level.txt
mydaoyipackage-0.0.3.dist-info/RECORD
