Metadata-Version: 2.1
Name: mydaoyipackage
Version: 0.0.3
Requires-Dist: requests
Requires-Dist: pytest ; python_version > "3.1"
